<annotation>
	<folder>images</folder>
	<filename>KXRV0588.JPG</filename>
	<path>C:\Users\mosae\USD Workes\AAI 521 Intro to Computer Vision\final project\images\KXRV0588.JPG</path>
	<source>
		<database>Unknown</database>
	</source>
	<size>
		<width>960</width>
		<height>1280</height>
		<depth>3</depth>
	</size>
	<segmented>0</segmented>
	<object>
		<name>LILY</name>
		<pose>Unspecified</pose>
		<truncated>0</truncated>
		<difficult>0</difficult>
		<bndbox>
			<xmin>272</xmin>
			<ymin>338</ymin>
			<xmax>541</xmax>
			<ymax>656</ymax>
		</bndbox>
	</object>
</annotation>
