<annotation>
	<folder>images</folder>
	<filename>MFYU5482.JPG</filename>
	<path>C:\Users\mosae\USD Workes\AAI 521 Intro to Computer Vision\final project\images\MFYU5482.JPG</path>
	<source>
		<database>Unknown</database>
	</source>
	<size>
		<width>768</width>
		<height>1024</height>
		<depth>3</depth>
	</size>
	<segmented>0</segmented>
	<object>
		<name>LILY</name>
		<pose>Unspecified</pose>
		<truncated>0</truncated>
		<difficult>0</difficult>
		<bndbox>
			<xmin>232</xmin>
			<ymin>46</ymin>
			<xmax>453</xmax>
			<ymax>298</ymax>
		</bndbox>
	</object>
</annotation>
